Metadata-Version: 2.1
Name: safersympify
Version: 0.1.18
Summary: Safer way to sympify unsanitized input
Home-page: https://github.com/jpackagebot/safersympify
Author: John Dory
Author-email: packagebot@gmail.com
License: UNKNOWN
Platform: UNKNOWN
Classifier: Programming Language :: Python :: 3
Classifier: License :: OSI Approved :: MIT License
Classifier: Operating System :: OS Independent
